{
  "id": "hoiquan",
  "url": "https://tinyurl.com/thapcam",
  "name": "Hội Quán TV",
  "color": "#1cb57a",
  "grid_number": 3,
  "image": {
    "type": "cover",
    "url": "https://kaytee1012.github.io/hoiquan_logo.png"
  },
  "notice": {
    "closeable": true,
    "icon": "https://kaytee1012.github.io/pngegg.png",
    "id": "notice",
    "link": "https://t.me/dqstore1",
    "text": "Nhóm Tele"
  },
  "groups": [
    {
      "id": "live",
      "name": "🔴 Live bóng đá",
      "display": "vertical",
      "grid_number": 2,
      "enable_detail": false,
      "channels": [
        {
          "id": "ch-c2728f66-f709-4eb9-ac37-76eb141e7e0d-135",
          "name": "⚽ Chengdu Rongcheng FC vs Shandong Taishan",
          "type": "single",
          "display": "thumbnail-only",
          "enable_detail": false,
          "image": {
            "padding": 1,
            "background_color": "#ececec",
            "display": "contain",
            "url": "https://cdn-img.cdnokvip.com/logos/36861_1gy3vkgfwve.PNG",
            "width": 1600,
            "height": 1200
          },
          "labels": [
            {
              "text": "● Live",
              "position": "top-left",
              "color": "#00ffffff",
              "text_color": "#ff0000"
            }
          ],
          "sources": [
            {
              "id": "src-c2728f66-f709-4eb9-ac37-76eb141e7e0d",
              "name": "Hội Quán",
              "contents": [
                {
                  "id": "cnt-c2728f66-f709-4eb9-ac37-76eb141e7e0d",
                  "name": "Chengdu Rongcheng FC vs Shandong Taishan",
                  "streams": [
                    {
                      "id": "str-c2728f66-f709-4eb9-ac37-76eb141e7e0d",
                      "name": "F",
                      "stream_links": [
                        {
                          "id": "lnk-c2728f66-f709-4eb9-ac37-76eb141e7e0d-m3u8",
                          "name": "Link 1",
                          "type": "hls",
                          "default": true,
                          "url": "https://hls.cdnfaster-a.live/live/LUUBI/index.m3u8?expire=1788427256&sign=e15f8b184dc9c61cc5dacfd962841ae1"
                        },
                        {
                          "id": "lnk-c2728f66-f709-4eb9-ac37-76eb141e7e0d-flv",
                          "name": "Link 2",
                          "type": "flv",
                          "default": false,
                          "url": "https://flv.cdnfaster-a.live/live/LUUBI.flv?expire=1788427256&sign=e15f8b184dc9c61cc5dacfd962841ae1"
                        }
                      ]
                    }
                  ]
                }
              ]
            }
          ]
        },
        {
          "id": "ch-c542a4e4-e70f-4fb9-b513-7bcaa3b48c66-298",
          "name": "⚽ Kyoto Sanga vs Kashiwa Reysol",
          "type": "single",
          "display": "thumbnail-only",
          "enable_detail": false,
          "image": {
            "padding": 1,
            "background_color": "#ececec",
            "display": "contain",
            "url": "https://cdn-img.cdnokvip.com/logos/2640_1hwerqcfbv2k.png",
            "width": 1600,
            "height": 1200
          },
          "labels": [
            {
              "text": "● Live",
              "position": "top-left",
              "color": "#00ffffff",
              "text_color": "#ff0000"
            }
          ],
          "sources": [
            {
              "id": "src-c542a4e4-e70f-4fb9-b513-7bcaa3b48c66",
              "name": "Hội Quán",
              "contents": [
                {
                  "id": "cnt-c542a4e4-e70f-4fb9-b513-7bcaa3b48c66",
                  "name": "Kyoto Sanga vs Kashiwa Reysol",
                  "streams": [
                    {
                      "id": "str-c542a4e4-e70f-4fb9-b513-7bcaa3b48c66",
                      "name": "F",
                      "stream_links": [
                        {
                          "id": "lnk-c542a4e4-e70f-4fb9-b513-7bcaa3b48c66-m3u8",
                          "name": "Link 1",
                          "type": "hls",
                          "default": true,
                          "url": "https://hls.cdnfaster-a.live/live/TAYMONKHANH/index.m3u8?expire=1788427256&sign=b79b5be508185d24f76a0b1effca53da"
                        },
                        {
                          "id": "lnk-c542a4e4-e70f-4fb9-b513-7bcaa3b48c66-flv",
                          "name": "Link 2",
                          "type": "flv",
                          "default": false,
                          "url": "https://flv.cdnfaster-a.live/live/TAYMONKHANH.flv?expire=1788427256&sign=b79b5be508185d24f76a0b1effca53da"
                        }
                      ]
                    }
                  ]
                }
              ]
            }
          ]
        },
        {
          "id": "ch-fd43ae4b-cc9f-4c83-892e-e86b03c22c2b-337",
          "name": "⚽ Chongqing Tonglianglong vs Beijing Guoan",
          "type": "single",
          "display": "thumbnail-only",
          "enable_detail": false,
          "image": {
            "padding": 1,
            "background_color": "#ececec",
            "display": "contain",
            "url": "https://cdn-img.cdnokvip.com/logos/61524_1hysdzw5hv1f.png",
            "width": 1600,
            "height": 1200
          },
          "labels": [
            {
              "text": "● Live",
              "position": "top-left",
              "color": "#00ffffff",
              "text_color": "#ff0000"
            }
          ],
          "sources": [
            {
              "id": "src-fd43ae4b-cc9f-4c83-892e-e86b03c22c2b",
              "name": "Hội Quán",
              "contents": [
                {
                  "id": "cnt-fd43ae4b-cc9f-4c83-892e-e86b03c22c2b",
                  "name": "Chongqing Tonglianglong vs Beijing Guoan",
                  "streams": [
                    {
                      "id": "str-fd43ae4b-cc9f-4c83-892e-e86b03c22c2b",
                      "name": "F",
                      "stream_links": [
                        {
                          "id": "lnk-fd43ae4b-cc9f-4c83-892e-e86b03c22c2b-m3u8",
                          "name": "Link 1",
                          "type": "hls",
                          "default": true,
                          "url": "https://hls.cdnfaster-a.live/live/VANCONAN/index.m3u8?expire=1830276060&sign=53991e2e589a2f7031dd37b82a585e33"
                        },
                        {
                          "id": "lnk-fd43ae4b-cc9f-4c83-892e-e86b03c22c2b-flv",
                          "name": "Link 2",
                          "type": "flv",
                          "default": false,
                          "url": "https://flv.cdnfaster-a.live/live/VANCONAN.flv?expire=1830276060&sign=53991e2e589a2f7031dd37b82a585e33"
                        }
                      ]
                    }
                  ]
                }
              ]
            }
          ]
        },
        {
          "id": "ch-359109925-368",
          "name": "⚽ Scotland vs Curacao",
          "type": "single",
          "display": "thumbnail-only",
          "enable_detail": false,
          "image": {
            "padding": 1,
            "background_color": "#ececec",
            "display": "contain",
            "url": "https://cdn-img.cdnokvip.com/logos/552_164984175759.png",
            "width": 1600,
            "height": 1200
          },
          "labels": [
            {
              "text": "● Live",
              "position": "top-left",
              "color": "#00ffffff",
              "text_color": "#ff0000"
            }
          ],
          "sources": [
            {
              "id": "src-359109925",
              "name": "Hội Quán",
              "contents": [
                {
                  "id": "cnt-359109925",
                  "name": "Scotland vs Curacao",
                  "streams": [
                    {
                      "id": "str-359109925",
                      "name": "F",
                      "stream_links": [
                        {
                          "id": "lnk-359109925-m3u8",
                          "name": "Link 1",
                          "type": "hls",
                          "default": true,
                          "url": "https://hls.cdnfaster-a.live/live/FERNANDO/index.m3u8?expire=1924930980&sign=bab24fb93b0be5c98af9138659989bcb"
                        },
                        {
                          "id": "lnk-359109925-flv",
                          "name": "Link 2",
                          "type": "flv",
                          "default": false,
                          "url": "https://flv.cdnfaster-a.live/live/FERNANDO.flv?expire=1924930980&sign=bab24fb93b0be5c98af9138659989bcb"
                        }
                      ]
                    }
                  ]
                }
              ]
            }
          ]
        },
        {
          "id": "ch-489484924-253",
          "name": "⚽ Arsenal Dzyarzhynsk vs Dinamo Minsk",
          "type": "single",
          "display": "thumbnail-only",
          "enable_detail": false,
          "image": {
            "padding": 1,
            "background_color": "#ececec",
            "display": "contain",
            "url": "https://cdn-img.cdnokvip.com/logos/40198_1h71mwa4sd1b.png",
            "width": 1600,
            "height": 1200
          },
          "labels": [
            {
              "text": "● Live",
              "position": "top-left",
              "color": "#00ffffff",
              "text_color": "#ff0000"
            }
          ],
          "sources": [
            {
              "id": "src-489484924",
              "name": "Hội Quán",
              "contents": [
                {
                  "id": "cnt-489484924",
                  "name": "Arsenal Dzyarzhynsk vs Dinamo Minsk",
                  "streams": [
                    {
                      "id": "str-489484924",
                      "name": "F",
                      "stream_links": [
                        {
                          "id": "lnk-489484924-m3u8",
                          "name": "Link 1",
                          "type": "hls",
                          "default": true,
                          "url": "https://hls.cdnfaster-a.live/live/NGUCA/index.m3u8?expire=1788427256&sign=abf9c93edd0de1c833f9ffc14381d526"
                        },
                        {
                          "id": "lnk-489484924-flv",
                          "name": "Link 2",
                          "type": "flv",
                          "default": false,
                          "url": "https://flv.cdnfaster-a.live/live/NGUCA.flv?expire=1788427256&sign=abf9c93edd0de1c833f9ffc14381d526"
                        }
                      ]
                    }
                  ]
                }
              ]
            }
          ]
        },
        {
          "id": "ch-211096928-328",
          "name": "⚽ Aalborg vs Herfolge Boldklub Koge",
          "type": "single",
          "display": "thumbnail-only",
          "enable_detail": false,
          "image": {
            "padding": 1,
            "background_color": "#ececec",
            "display": "contain",
            "url": "https://cdn-img.cdnokvip.com/logos/220_1gtg0npad1m.png",
            "width": 1600,
            "height": 1200
          },
          "labels": [
            {
              "text": "● Live",
              "position": "top-left",
              "color": "#00ffffff",
              "text_color": "#ff0000"
            }
          ],
          "sources": [
            {
              "id": "src-211096928",
              "name": "Hội Quán",
              "contents": [
                {
                  "id": "cnt-211096928",
                  "name": "Aalborg vs Herfolge Boldklub Koge",
                  "streams": [
                    {
                      "id": "str-211096928",
                      "name": "F",
                      "stream_links": [
                        {
                          "id": "lnk-211096928-m3u8",
                          "name": "Link 1",
                          "type": "hls",
                          "default": true,
                          "url": "https://hls.cdnfaster-a.live/live/VOTONG/index.m3u8?expire=1891347600&sign=cbb47d2000b9576a7b34114624ff8299"
                        },
                        {
                          "id": "lnk-211096928-flv",
                          "name": "Link 2",
                          "type": "flv",
                          "default": false,
                          "url": "https://flv.cdnfaster-a.live/live/VOTONG.flv?expire=1891347600&sign=cbb47d2000b9576a7b34114624ff8299"
                        }
                      ]
                    }
                  ]
                }
              ]
            }
          ]
        },
        {
          "id": "ch-407998924-358",
          "name": "⚽ FK MAS Taborsko vs Banik Ostrava",
          "type": "single",
          "display": "thumbnail-only",
          "enable_detail": false,
          "image": {
            "padding": 1,
            "background_color": "#ececec",
            "display": "contain",
            "url": "https://cdn-img.cdnokvip.com/logos/17714_1gtqm9kx5j2a.png",
            "width": 1600,
            "height": 1200
          },
          "labels": [
            {
              "text": "● Live",
              "position": "top-left",
              "color": "#00ffffff",
              "text_color": "#ff0000"
            }
          ],
          "sources": [
            {
              "id": "src-407998924",
              "name": "Hội Quán",
              "contents": [
                {
                  "id": "cnt-407998924",
                  "name": "FK MAS Taborsko vs Banik Ostrava",
                  "streams": [
                    {
                      "id": "str-407998924",
                      "name": "F",
                      "stream_links": [
                        {
                          "id": "lnk-407998924-m3u8",
                          "name": "Link 1",
                          "type": "hls",
                          "default": true,
                          "url": "https://hls.cdnfaster-a.live/live/MAYBACH/index.m3u8?expire=1923468720&sign=862d9b5fa441bf644b6c2fbcec08487b"
                        },
                        {
                          "id": "lnk-407998924-flv",
                          "name": "Link 2",
                          "type": "flv",
                          "default": false,
                          "url": "https://flv.cdnfaster-a.live/live/MAYBACH.flv?expire=1923468720&sign=862d9b5fa441bf644b6c2fbcec08487b"
                        }
                      ]
                    }
                  ]
                }
              ]
            }
          ]
        },
        {
          "id": "ch-332744921-377",
          "name": "⚽ Shenzhen Xinpengcheng vs Qingdao Manatee",
          "type": "single",
          "display": "thumbnail-only",
          "enable_detail": false,
          "image": {
            "padding": 1,
            "background_color": "#ececec",
            "display": "contain",
            "url": "https://cdn-img.cdnokvip.com/logos/34003_1j0ytnk9yw25.png",
            "width": 1600,
            "height": 1200
          },
          "labels": [
            {
              "text": "● Live",
              "position": "top-left",
              "color": "#00ffffff",
              "text_color": "#ff0000"
            }
          ],
          "sources": [
            {
              "id": "src-332744921",
              "name": "Hội Quán",
              "contents": [
                {
                  "id": "cnt-332744921",
                  "name": "Shenzhen Xinpengcheng vs Qingdao Manatee",
                  "streams": [
                    {
                      "id": "str-332744921",
                      "name": "F",
                      "stream_links": [
                        {
                          "id": "lnk-332744921-m3u8",
                          "name": "Link 1",
                          "type": "hls",
                          "default": true,
                          "url": "https://hls.cdnfaster-a.live/live/PHIHO/index.m3u8?expire=2556118740&sign=ebc20a588b7a62eb65d12f7372d39a3f"
                        },
                        {
                          "id": "lnk-332744921-flv",
                          "name": "Link 2",
                          "type": "flv",
                          "default": false,
                          "url": "https://flv.cdnfaster-a.live/live/PHIHO.flv?expire=2556118740&sign=ebc20a588b7a62eb65d12f7372d39a3f"
                        }
                      ]
                    }
                  ]
                }
              ]
            }
          ]
        },
        {
          "id": "ch-322744920-290",
          "name": "⚽ Qingdao West Coast vs Shanghai Shenhua",
          "type": "single",
          "display": "thumbnail-only",
          "enable_detail": false,
          "image": {
            "padding": 1,
            "background_color": "#ececec",
            "display": "contain",
            "url": "https://cdn-img.cdnokvip.com/logos/41556_1h1n1m7x0f8.png",
            "width": 1600,
            "height": 1200
          },
          "labels": [
            {
              "text": "● Live",
              "position": "top-left",
              "color": "#00ffffff",
              "text_color": "#ff0000"
            }
          ],
          "sources": [
            {
              "id": "src-322744920",
              "name": "Hội Quán",
              "contents": [
                {
                  "id": "cnt-322744920",
                  "name": "Qingdao West Coast vs Shanghai Shenhua",
                  "streams": [
                    {
                      "id": "str-322744920",
                      "name": "F",
                      "stream_links": [
                        {
                          "id": "lnk-322744920-m3u8",
                          "name": "Link 1",
                          "type": "hls",
                          "default": true,
                          "url": "https://hls.cdnfaster-a.live/live/KEVILL/index.m3u8?expire=1788427256&sign=189afcf7f800d4c6c8a5aa97649a110799"
                        },
                        {
                          "id": "lnk-322744920-flv",
                          "name": "Link 2",
                          "type": "flv",
                          "default": false,
                          "url": "https://flv.cdnfaster-a.live/live/KEVILL.flv?expire=1788427256&sign=189afcf7f800d4c6c8a5aa97649a110799"
                        }
                      ]
                    }
                  ]
                }
              ]
            }
          ]
        },
        {
          "id": "ch-72bb2412-7e17-4b5e-ae24-862d57ffbd53-81",
          "name": "⚽ Qingdao West Coast vs Shanghai Shenhua",
          "type": "single",
          "display": "thumbnail-only",
          "enable_detail": false,
          "image": {
            "padding": 1,
            "background_color": "#ececec",
            "display": "contain",
            "url": "https://cdn-img.cdnokvip.com/logos/41556_1h1n1m7x0f8.png",
            "width": 1600,
            "height": 1200
          },
          "labels": [
            {
              "text": "● Live",
              "position": "top-left",
              "color": "#00ffffff",
              "text_color": "#ff0000"
            }
          ],
          "sources": [
            {
              "id": "src-72bb2412-7e17-4b5e-ae24-862d57ffbd53",
              "name": "Hội Quán",
              "contents": [
                {
                  "id": "cnt-72bb2412-7e17-4b5e-ae24-862d57ffbd53",
                  "name": "Qingdao West Coast vs Shanghai Shenhua",
                  "streams": [
                    {
                      "id": "str-72bb2412-7e17-4b5e-ae24-862d57ffbd53",
                      "name": "F",
                      "stream_links": [
                        {
                          "id": "lnk-72bb2412-7e17-4b5e-ae24-862d57ffbd53-m3u8",
                          "name": "Link 1",
                          "type": "hls",
                          "default": true,
                          "url": "https://hls.cdnfaster-a.live/live/TRIEUTULONG/index.m3u8?expire=1788427256&sign=45e4fdc4bdb8472f513ccc78f57f6070"
                        },
                        {
                          "id": "lnk-72bb2412-7e17-4b5e-ae24-862d57ffbd53-flv",
                          "name": "Link 2",
                          "type": "flv",
                          "default": false,
                          "url": "https://flv.cdnfaster-a.live/live/TRIEUTULONG.flv?expire=1788427256&sign=45e4fdc4bdb8472f513ccc78f57f6070"
                        }
                      ]
                    }
                  ]
                }
              ]
            }
          ]
        },
        {
          "id": "ch-202744928-292",
          "name": "⚽ Henan Football Club vs Zhejiang Professional FC",
          "type": "single",
          "display": "thumbnail-only",
          "enable_detail": false,
          "image": {
            "padding": 1,
            "background_color": "#ececec",
            "display": "contain",
            "url": "https://cdn-img.cdnokvip.com/logos/495_1j39p5ccv415.png",
            "width": 1600,
            "height": 1200
          },
          "labels": [
            {
              "text": "● Live",
              "position": "top-left",
              "color": "#00ffffff",
              "text_color": "#ff0000"
            }
          ],
          "sources": [
            {
              "id": "src-202744928",
              "name": "Hội Quán",
              "contents": [
                {
                  "id": "cnt-202744928",
                  "name": "Henan Football Club vs Zhejiang Professional FC",
                  "streams": [
                    {
                      "id": "str-202744928",
                      "name": "F",
                      "stream_links": [
                        {
                          "id": "lnk-202744928-m3u8",
                          "name": "Link 1",
                          "type": "hls",
                          "default": true,
                          "url": "https://hls.cdnfaster-a.live/live/LYUNG1/index.m3u8?expire=1788427256&sign=d5c6932fefdcb98268754f4ccd4aa45d"
                        },
                        {
                          "id": "lnk-202744928-flv",
                          "name": "Link 2",
                          "type": "flv",
                          "default": false,
                          "url": "https://flv.cdnfaster-a.live/live/LYUNG1.flv?expire=1788427256&sign=d5c6932fefdcb98268754f4ccd4aa45d"
                        }
                      ]
                    }
                  ]
                }
              ]
            }
          ]
        },
        {
          "id": "ch-6f01050a-8b1d-4944-bf06-608c7cb9b2ff-101",
          "name": "⚽ Henan Football Club vs Zhejiang Professional FC",
          "type": "single",
          "display": "thumbnail-only",
          "enable_detail": false,
          "image": {
            "padding": 1,
            "background_color": "#ececec",
            "display": "contain",
            "url": "https://cdn-img.cdnokvip.com/logos/495_1j39p5ccv415.png",
            "width": 1600,
            "height": 1200
          },
          "labels": [
            {
              "text": "● Live",
              "position": "top-left",
              "color": "#00ffffff",
              "text_color": "#ff0000"
            }
          ],
          "sources": [
            {
              "id": "src-6f01050a-8b1d-4944-bf06-608c7cb9b2ff",
              "name": "Hội Quán",
              "contents": [
                {
                  "id": "cnt-6f01050a-8b1d-4944-bf06-608c7cb9b2ff",
                  "name": "Henan Football Club vs Zhejiang Professional FC",
                  "streams": [
                    {
                      "id": "str-6f01050a-8b1d-4944-bf06-608c7cb9b2ff",
                      "name": "F",
                      "stream_links": [
                        {
                          "id": "lnk-6f01050a-8b1d-4944-bf06-608c7cb9b2ff-m3u8",
                          "name": "Link 1",
                          "type": "hls",
                          "default": true,
                          "url": "https://hls.cdnfaster-a.live/live/QUANVU/index.m3u8?expire=1788427256&sign=056d097a0bbbd810493fd64ccf4831b7"
                        },
                        {
                          "id": "lnk-6f01050a-8b1d-4944-bf06-608c7cb9b2ff-flv",
                          "name": "Link 2",
                          "type": "flv",
                          "default": false,
                          "url": "https://flv.cdnfaster-a.live/live/QUANVU.flv?expire=1788427256&sign=056d097a0bbbd810493fd64ccf4831b7"
                        }
                      ]
                    }
                  ]
                }
              ]
            }
          ]
        }
      ]
    }
  ]
}